frills/__init__.py
frills/debugging.py
frills/graphics.py
frills/maths.py
frills-1.2.0.dist-info/LICENSE
frills-1.2.0.dist-info/METADATA
frills-1.2.0.dist-info/WHEEL
frills-1.2.0.dist-info/top_level.txt
frills-1.2.0.dist-info/RECORD
