Metadata-Version: 2.1
Name: frills
Version: 1.2.0
Summary: Helpful utilities for python development
Author-email: Seb Gregory <sebgregory4@gmail.com>
Classifier: Programming Language :: Python :: 3
Classifier: License :: OSI Approved :: MIT License
Classifier: Operating System :: OS Independent
Requires-Python: >=3.7
License-File: LICENSE
Requires-Dist: opencv-python
Requires-Dist: numpy
